donkit/chunker/__init__.py
donkit/chunker/config.py
donkit/chunker/langchain_splitting.py.backup
donkit/chunker/splitting.py
donkit_chunker-0.1.7.dist-info/METADATA
donkit_chunker-0.1.7.dist-info/WHEEL
donkit_chunker-0.1.7.dist-info/RECORD
