Metadata-Version: 2.3
Name: donkit-chunker
Version: 0.1.7
Summary: Chunking utilities for Donkit RagOps pipelines
License: MIT
Author: Donkit AI
Author-email: opensource@donkit.ai
Requires-Python: >=3.12,<4.0
Classifier: License :: OSI Approved :: MIT License
Classifier: Programming Language :: Python :: 3
Classifier: Programming Language :: Python :: 3.12
Classifier: Programming Language :: Python :: 3.13
Requires-Dist: aiofiles (>=25.1.0,<26.0.0)
Requires-Dist: langchain-core (>=0.3.27,<0.4.0)
Requires-Dist: langchain-experimental (>=0.3.4,<0.4.0)
Requires-Dist: langchain-text-splitters (>=0.3.0,<0.4.0)
Requires-Dist: loguru (>=0.7.3,<0.8.0)
Requires-Dist: pydantic (>=2.7.4,<3.0.0)
Requires-Dist: toonify[pydantic] (>=1.5.1,<2.0.0)
